{
  "date": "2026-07-12",
  "nowcast": 4.25,
  "latest_actual": 4.27,
  "rmse_historical": 0.57,
  "mae_historical": 0.4,
  "top_features": [
    {
      "feature": "MICH",
      "importance": 0.41370150446891785
    },
    {
      "feature": "T5YIE",
      "importance": 0.13013456761837006
    },
    {
      "feature": "HOUST",
      "importance": 0.09848769009113312
    },
    {
      "feature": "CPI_lag1",
      "importance": 0.0727400928735733
    },
    {
      "feature": "PAYEMS_mom",
      "importance": 0.05572133883833885
    }
  ],
  "data_available": {
    "monthly_series": 9,
    "daily_series": 5,
    "training_samples": 184
  }
}